[
  {
    "id":1,
    "img":"../img/hotWater.jpg",
    "title":"米家恒温电水壶 白色",
    "desc":"一杯水的温度，刚刚好",
    "price":"189",
    "delPrice":"199"
  },
  {
  "id":1,
  "img":"../img/29087f25-a8b1-b285-00fa-9e144076e2c4.jpg",
  "title":"小米手环 2 黑色",
  "desc":"OLED显示屏，触摸操作",
  "price":"142",
  "delPrice":"199"
},
  {
    "id":1,
    "img":"../img/4544f541-f2e1-f423-5cbf-88fe33c5e110.jpg",
    "title":"空气净化器滤芯",
    "desc":"阻挡细菌，有效去除甲醛",
    "price":"159",
    "delPrice":"169"
  },
  {
    "id":1,
    "img":"../img/7e0a6709-90db-03d4-26d4-c2d914a57fc0.jpg",
    "title":"小米笔记本 Air13.3 i7 8G 256G  ",
    "desc":"轻薄全金属，超长待机",
    "price":"5588",
    "delPrice":"5999"
  },
  {
    "id":1,
    "img":"../img/T1WPxjBbAT1RXrhCrK.jpg",
    "title":"1more入耳式耳机(活塞复刻板) 深空灰",
    "desc":"“听歌神器”重回视野",
    "price":"94",
    "delPrice":"99"
  },
  {
    "id":1,
    "img":"../img/note2320x220.png",
    "title":"小米手机 Note3",
    "desc":"全金属机身",
    "price":"1899",
    "delPrice":"1999"
  },
  {
    "id":1,
    "img":"../img/80x80youxichuantu.png",
    "title":"小米游戏本 15.6英寸",
    "desc":"窄边框全高清屏",
    "price":"8999",
    "delPrice":"9999"
  },
  {
    "id":1,
    "img":"../img/b315ba2c-3dc0-1352-3fbf-b23ffad1bb0f.jpg",
    "title":"米家空气净化器pro 白色",
    "desc":"大空间，快循环",
    "price":"1399",
    "delPrice":"1499"
  }
]